{"paths":{},"types":[],"uuids":["19et9IxbJBTItMOGM4tGul","71VhFCTINJM6/Ky3oX9nBT","73dTOhcldOLoooVKlqEPS4","77Rszmy51Bi6fL3ybHke+D","7dawjASRZKeK0uAHn196A5","87di1yEjpGGqdXsKtPCsBK","8aKfdDaRhIqZvRrS2cZQg5","9a56MEC9FP44hJgnkYuN5B","b4P/PCArtIdIH38t6mlw8Y","b5ruMGaCFPcIaLM+JfIzpk","ceFoyO3yhEDpQKY9D7Thas","d8HsitJHxOYqo801xBk8ev","dbVBoAU7FIkrS/mFJ/QqYg","e8Ueib+qJEhL6mXAHdnwbi","ed0hW5J5ZKBar1gflskoHO","02delMVqdBD70a/HSD99FK","0aZ+HILllGa6pQN3GiMJp2","0fnc1qcPJNLb+I6H+tEU0C","29FYIk+N1GYaeWH/q1NxQO","36aLOI9FtK0ZKWv96GXQAy","48O9oQdhRIaY40TJCbFYnt","7aAeVzdTNN7bMCwi0M1bBW","9bvaMerUlDyary99mJa6xp","a2MjXRFdtLlYQ5ouAFv/+R","abp8tqx+VIZZ7CC7NgfcZx","b0IEjY6GZPOK7UPKYjK0Vb","b6KTs1QutItKWcBUhG6CR7","c3eyTHqUBOkrUzAt6YBBo9","c6379gyYtOqbOTES+6PtAo","e97GVMl6JHh5Ml5qEDdSGa","ecpdLyjvZBwrvm+cedCcQy","f0BIwQ8D5Ml7nTNQbh1YlS","ffDpHHVcZAhqOfy25Fe4w7"],"scenes":{"db://assets/scene/0.fire":6},"redirect":[15,0,30,0],"deps":["internal"],"packs":{"02b392c11":[16,17,18,19,20,21,6,22,23,24,25,26,27,28,29,31,32],"0d1900e21":[0,1,2,3,4,5,7,8,9,10,11,12,13,14]},"name":"main","importBase":"import","nativeBase":"native","debug":false,"isZip":false,"encrypted":false,"versions":{"import":["02b392c11","95434","0d1900e21","1a978"],"native":[0,"53c9d",1,"c06a9",2,"bc8d5",3,"430b6",4,"309ad",5,"39a82",7,"3f09d",8,"83fcc",9,"974a3",10,"09338",11,"cdbc9",12,"78b94",13,"90cf4",14,"17df6"]}}